metasim/__init__.py
metasim/constants.py
metasim/types.py
metasim/cfg/__init__.py
metasim/cfg/lights.py
metasim/cfg/objects.py
metasim/cfg/randomization.py
metasim/cfg/render.py
metasim/cfg/scenario.py
metasim/cfg/cameras/__init__.py
metasim/cfg/cameras/camera.py
metasim/cfg/checkers/__init__.py
metasim/cfg/checkers/base_checker.py
metasim/cfg/checkers/checker_operators.py
metasim/cfg/checkers/checkers.py
metasim/cfg/checkers/detectors.py
metasim/cfg/robots/__init__.py
metasim/cfg/robots/ant_metacfg.py
metasim/cfg/robots/base_robot_metacfg.py
metasim/cfg/robots/fetch_metacfg.py
metasim/cfg/robots/franka_metacfg.py
metasim/cfg/robots/franka_slide_urdf_metacfg.py
metasim/cfg/robots/franka_slide_urdf_sapien_metacfg.py
metasim/cfg/robots/franka_urdf_metacfg.py
metasim/cfg/robots/franka_urdf_sapien_metacfg.py
metasim/cfg/robots/franka_with_gripper_extension_metacfg.py
metasim/cfg/robots/google_robot_static_metacfg.py
metasim/cfg/robots/h1_2_without_hand_metacfg.py
metasim/cfg/robots/h1_metacfg.py
metasim/cfg/robots/h1_simple_hand_metacfg.py
metasim/cfg/robots/iiwa_metacfg.py
metasim/cfg/robots/sawyer_metacfg.py
metasim/cfg/robots/sawyer_mujoco_metacfg.py
metasim/cfg/robots/ur5e_2f85_metacfg.py
metasim/cfg/robots/walker_metacfg.py
metasim/cfg/scenes/__init__.py
metasim/cfg/scenes/base_scene_metacfg.py
metasim/cfg/scenes/tapwater_scene_131_metacfg.py
metasim/cfg/scenes/tapwater_scene_138_metacfg.py
metasim/cfg/scenes/tapwater_scene_144_metacfg.py
metasim/cfg/scenes/tapwater_scene_152_metacfg.py
metasim/cfg/scenes/tapwater_scene_155_metacfg.py
metasim/cfg/tasks/__init__.py
metasim/cfg/tasks/base_task_metacfg.py
metasim/cfg/tasks/arnold/__init__.py
metasim/cfg/tasks/arnold/arnold_pickup_object.py
metasim/cfg/tasks/arnold/arnold_reorient_object.py
metasim/cfg/tasks/arnold/arnold_task_metacfg.py
metasim/cfg/tasks/calvin/__init__.py
metasim/cfg/tasks/calvin/calvin.py
metasim/cfg/tasks/calvin/scene/scene_A.py
metasim/cfg/tasks/calvin/scene/scene_B.py
roboverse_py-0.1.17.dist-info/LICENSE
roboverse_py-0.1.17.dist-info/METADATA
roboverse_py-0.1.17.dist-info/WHEEL
roboverse_py-0.1.17.dist-info/top_level.txt
roboverse_py-0.1.17.dist-info/RECORD
